altest/__init__.py
altest-0.1.0.dist-info/WHEEL
altest-0.1.0.dist-info/METADATA
altest-0.1.0.dist-info/RECORD
