Metadata-Version: 2.1
Name: altest
Version: 0.1.0
Summary: 
Author: Your Name
Author-email: you@example.com
Requires-Python: >=3.8,<4.0
Classifier: Programming Language :: Python :: 3
Classifier: Programming Language :: Python :: 3.8
Classifier: Programming Language :: Python :: 3.9
Provides-Extra: all
Provides-Extra: auth
Provides-Extra: chatdsl
Provides-Extra: parser
Requires-Dist: PyYAML (==5.3.1)
Requires-Dist: aiobotocore (==1.3.3)
Requires-Dist: aiosqlite (==0.16.0)
Requires-Dist: databases (==0.4.2)
Requires-Dist: discord.py (==1.6.0); extra == "chatdsl" or extra == "all"
Requires-Dist: emoji (==1.2.0); extra == "chatdsl" or extra == "all"
Requires-Dist: fastapi (==0.63.0); extra == "auth" or extra == "all"
Requires-Dist: httpx (==0.18.2)
Requires-Dist: matrix-nio (==0.18.6); extra == "chatdsl" or extra == "all"
Requires-Dist: pycryptodome (==3.10.1)
Requires-Dist: pydantic (==1.7.3)
Requires-Dist: pyduckling-native (==0.1.0); extra == "parser" or extra == "all"
Requires-Dist: pyjwt (==2.0.1); extra == "auth" or extra == "all"
Requires-Dist: spacy (==3.0.6); extra == "parser" or extra == "all"
Requires-Dist: sqlalchemy (==1.3.23)
Requires-Dist: structlog (==20.1.0)
Requires-Dist: websockets (==9.1)
